{
	"$schema": "https://schemas.wp.org/trunk/block.json",
	"apiVersion": 2,
	"name": "learnpress/duration-single-course",
	"title": "Duration Single Course",
	"category": "lp-single-course-category",
	"description": "Renders template Duration Single Course PHP templates.",
	"textdomain": "learnpress",
	"keywords": ["duration single course", "learnpress"],
	"attributes": {
		"courseId": {
			"type": "number"
		}
	},
	"usesContext": [],
	"supports": {
		"inserter": true,
		"reusable": true,
		"reorder": true,
		"html": false,
		"multiple": true
	}
}
