{
	"$schema": "https://schemas.wp.org/trunk/block.json",
	"apiVersion": 2,
	"name": "learnpress/level-single-course",
	"title": "Level Course",
	"category": "lp-single-course-category",
	"description": "Renders template Level Course PHP templates.",
	"textdomain": "learnpress",
	"keywords": ["level single course", "learnpress"],
	"attributes": {
		"layout": {
			"type": "string",
			"default": "classic"
		}
	},
	"usesContext": [],
	"supports": {
		"inserter": true,
		"reusable": true,
		"reorder": true,
		"html": false,
		"multiple": true
	},
	"ancestor": ["learnpress/lp-single-course"]
}
